MANIFEST.in
README.md
rq.yaml
setup.py
timmy-config-default.yaml
timmy-config.yaml
db/md5/6.0/ubuntu.filter
db/md5/6.1/ubuntu.filter
db/md5/7.0/ubuntu.filter
db/md5/8.0/centos.filter
db/md5/8.0/ubuntu.filter
db/versions/6.0/centos.sqlite
db/versions/6.0/ubuntu.sqlite
db/versions/6.1/centos.sqlite
db/versions/6.1/ubuntu.sqlite
db/versions/7.0/centos.sqlite
db/versions/7.0/ubuntu.sqlite
db/versions/8.0/centos.sqlite
db/versions/8.0/ubuntu.sqlite
db/versions/9.0/9.0-centos.sqlite
db/versions/9.0/9.0-ubuntu.sqlite
db/versions/9.0/centos.sqlite
db/versions/9.0/ubuntu.sqlite
db/versions/9.2/9.0-centos.sqlite
db/versions/9.2/9.0-ubuntu.sqlite
db/versions/9.2/centos.sqlite
db/versions/9.2/ubuntu.sqlite
rq/scripts/packagelist-centos
rq/scripts/packagelist-ubuntu
rq/scripts/packages-md5-verify-centos
rq/scripts/packages-md5-verify-ubuntu
timmy_customtest/__init__.py
timmy_customtest/customtest.py
timmy_customtest/vercmp.py
timmy_customtest.egg-info/PKG-INFO
timmy_customtest.egg-info/SOURCES.txt
timmy_customtest.egg-info/dependency_links.txt
timmy_customtest.egg-info/entry_points.txt
timmy_customtest.egg-info/requires.txt
timmy_customtest.egg-info/top_level.txt