Metadata-Version: 1.0
Name: timmy-customtest
Version: 1.2.15
Summary: UNKNOWN
Home-page: https://github.com/f3flight/timmy-customtest
Author: Dmitry Sutyagin
Author-email: f3flight@gmail.com
License: Apache2
Platform: UNKNOWN
